moonwatcher/__init__.py
moonwatcher/annotations.py
moonwatcher/base/base.py
moonwatcher/caltech.sh
moonwatcher/check.py
moonwatcher/coco.sh
moonwatcher/configs/demo_classification.json
moonwatcher/configs/demo_detection.json
moonwatcher/configs/imagenet_to_stl.json
moonwatcher/datapoint.py
moonwatcher/dataset/dataset.py
moonwatcher/dataset/metadata.py
moonwatcher/demo_classification.py
moonwatcher/demo_detection.py
moonwatcher/inference/inference.py
moonwatcher/main_upload_images.py
moonwatcher/metric.py
moonwatcher/model/model.py
moonwatcher/utils/api_connector.py
moonwatcher/utils/bbox_utils.py
moonwatcher/utils/data.py
moonwatcher/utils/data_storage.py
moonwatcher/utils/helpers.py
moonwatcher/utils/image_upload.py
moonwatcher/utils/imagenet_to_stl.py
moonwatcher-0.1.0a1.dist-info/LICENSE
moonwatcher-0.1.0a1.dist-info/METADATA
moonwatcher-0.1.0a1.dist-info/WHEEL
moonwatcher-0.1.0a1.dist-info/RECORD
