Metadata-Version: 2.1
Name: moonwatcher
Version: 0.1.0a1
Summary: 
Home-page: https://www.moonwatcher.ai
License: Apache-2.0
Author: Leon Steffen
Author-email: hello@moonwatcher.ai
Requires-Python: >=3.10,<4.0
Classifier: License :: OSI Approved :: Apache Software License
Classifier: Programming Language :: Python :: 3
Classifier: Programming Language :: Python :: 3.10
Classifier: Programming Language :: Python :: 3.11
Classifier: Programming Language :: Python :: 3.12
Requires-Dist: gdown (>=5.1.0,<6.0.0)
Requires-Dist: numpy (>=1.26.4,<2.0.0)
Requires-Dist: opencv-python (>=4.9.0.80,<5.0.0.0)
Requires-Dist: pandas (>=2.2.1,<3.0.0)
Requires-Dist: pycocotools (>=2.0.7,<3.0.0)
Requires-Dist: pytest (>=8.1.1,<9.0.0)
Requires-Dist: python-dotenv (>=1.0.1,<2.0.0)
Requires-Dist: pytz (>=2024.1,<2025.0)
Requires-Dist: requests (>=2.31.0,<3.0.0)
Requires-Dist: scikit-learn (>=1.4.1.post1,<2.0.0)
Requires-Dist: setuptools (>=69.2.0,<70.0.0)
Requires-Dist: timm (>=0.9.16,<0.10.0)
Requires-Dist: torch (>=2.2.2,<3.0.0)
Requires-Dist: torchmetrics (>=1.3.2,<2.0.0)
Requires-Dist: torchvision (>=0.17.2,<0.18.0)
Requires-Dist: tqdm (>=4.66.2,<5.0.0)
Requires-Dist: transformers (>=4.39.3,<5.0.0)
Project-URL: Issues, https://github.com/moonwatcher-ai/moonwatcher/issues
Project-URL: Repository, https://github.com/moonwatcher-ai/moonwatcher
